[
    {
        "id": 1,
        "name": "Producto 1",
        "description": "Descripción del producto 1",
        "offer": 0.10,
        "price": 19.99,
        "image": "img/ordenador-personal.png"
    },
    {
        "id": 2,
        "name": "Producto 2",
        "description": "Descripción del producto 2",
        "offer": 0.10,
        "price": 24.99,
        "image": "img/URVAR-L.png"
    },
    {
        "id": 3,
        "name": "Producto 3",
        "description": "Descripción del producto 3",
        "offer": 0.10,
        "price": 29.99,
        "image": "img/ordenador-personal.png"
    },
    {
        "id": 4,
        "name": "Producto 4",
        "description": "Descripción del producto 4",
        "offer": 0,
        "price": 24.99,
        "image": "img/offer.webp"
    },
    {
        "id": 6,
        "name": "Producto 4",
        "description": "Descripción del producto 4",
        "offer": 0,
        "price": 24.99,
        "image": "img/offer.webp"
    },
    {
        "id": 7,
        "name": "Producto 4",
        "description": "Descripción del producto 4",
        "offer": 0,
        "price": 24.99,
        "image": "img/offer.webp"
    },
    {
        "id": 8,
        "name": "Producto 4",
        "description": "Descripción del producto 4",
        "offer": 0,
        "price": 24.99,
        "image": "img/offer.webp"
    },
    {
        "id": 9,
        "name": "Producto 4",
        "description": "Descripción del producto 4",
        "offer": 0,
        "price": 24.99,
        "image": "img/offer.webp"
    },
    {
        "id": 10,
        "name": "Producto 4",
        "description": "Descripción del producto 4",
        "offer": 0,
        "price": 24.99,
        "image": "img/offer.webp"
    },
    {
        "id": 11,
        "name": "Producto 4",
        "description": "Descripción del producto 4",
        "offer": 0,
        "price": 24.99,
        "image": "img/offer.webp"
    },
    {
        "id": 12,
        "name": "Producto 4",
        "description": "Descripción del producto 4",
        "offer": 0,
        "price": 24.99,
        "image": "img/offer.webp"
    }
]